codeEEW_parser/__init__.py
codeEEW_parser/parser.py
codeeew_parser-0.1.1.dist-info/METADATA
codeeew_parser-0.1.1.dist-info/WHEEL
codeeew_parser-0.1.1.dist-info/top_level.txt
codeeew_parser-0.1.1.dist-info/RECORD
